{
  "kind": "sequence",
  "name": "has parameters",
  "args": {
    "locals": {
      "kind": "scope_declaration",
      "args": {},
      "body": [
        {
          "kind": "parameter_declaration",
          "args": {
            "label": "parent",
            "default_value": {
              "kind": "coordinate",
              "args": {
                "x": 9,
                "y": 9,
                "z": 9
              }
            }
          }
        }
      ]
    }
  },
  "body": [
    {
      "kind": "move_absolute",
      "args": {
        "speed": 100,
        "location": {
          "kind": "identifier",
          "args": {
            "label": "parent"
          }
        },
        "offset": {
          "kind": "coordinate",
          "args": {
            "x": 0,
            "y": 0,
            "z": 0
          }
        }
      }
    }
  ]
}
